optpricing/__init__.py
optpricing/config.py
optpricing/atoms/__init__.py
optpricing/atoms/bond.py
optpricing/atoms/option.py
optpricing/atoms/rate.py
optpricing/atoms/stock.py
optpricing/calibration/__init__.py
optpricing/calibration/calibrator.py
optpricing/calibration/fit_jump_parameters.py
optpricing/calibration/fit_market_params.py
optpricing/calibration/iv_surface.py
optpricing/calibration/technique_selector.py
optpricing/calibration/vectorized_bsm_iv.py
optpricing/calibration/vectorized_integration_iv.py
optpricing/calibration/vectorized_pricer.py
optpricing/cli/__init__.py
optpricing/cli/main.py
optpricing/cli/commands/__init__.py
optpricing/cli/commands/backtest.py
optpricing/cli/commands/calibrate.py
optpricing/cli/commands/dashboard.py
optpricing/cli/commands/data.py
optpricing/cli/commands/demo.py
optpricing/cli/commands/price.py
optpricing/cli/commands/tools.py
optpricing/dashboard/Home.py
optpricing/dashboard/__init__.py
optpricing/dashboard/plots.py
optpricing/dashboard/service.py
optpricing/dashboard/widgets.py
optpricing/dashboard/pages/1_Pricer_and_Greeks.py
optpricing/dashboard/pages/2_Calibration_and_IV.py
optpricing/dashboard/pages/3_Market_Analytics.py
optpricing/dashboard/pages/4_Model_Fitting.py
optpricing/dashboard/pages/5_Term_Structure.py
optpricing/dashboard/pages/__init__.py
optpricing/data/__init__.py
optpricing/data/historical_manager.py
optpricing/data/market_data_manager.py
optpricing/models/__init__.py
optpricing/models/bates.py
optpricing/models/blacks_approx.py
optpricing/models/bsm.py
optpricing/models/cev.py
optpricing/models/cgmy.py
optpricing/models/cir.py
optpricing/models/dupire_local.py
optpricing/models/heston.py
optpricing/models/hyperbolic.py
optpricing/models/kou.py
optpricing/models/merton_jump.py
optpricing/models/nig.py
optpricing/models/perpetual_put.py
optpricing/models/sabr.py
optpricing/models/sabr_jump.py
optpricing/models/vasicek.py
optpricing/models/vg.py
optpricing/models/base/__init__.py
optpricing-2.3.2.dist-info/licenses/LICENSE
optpricing-2.3.2.dist-info/METADATA
optpricing-2.3.2.dist-info/WHEEL
optpricing-2.3.2.dist-info/entry_points.txt
optpricing-2.3.2.dist-info/top_level.txt
optpricing-2.3.2.dist-info/RECORD
