Metadata-Version: 2.4
Name: optpricing
Version: 2.3.2
Summary: A financial options pricing and analysis library.
Author-email: Diljit Singh <first_last22@google.com>
License: # MIT LICENSE
Project-URL: Homepage, https://diljit22.github.io/quantfin/
Classifier: Programming Language :: Python :: 3
Classifier: License :: OSI Approved :: MIT License
Classifier: Operating System :: OS Independent
Classifier: Topic :: Office/Business :: Financial :: Investment
Requires-Python: >=3.10
License-File: LICENSE
Requires-Dist: numpy~=2.2.5
Requires-Dist: scipy~=1.15.2
Requires-Dist: pandas~=2.2.3
Requires-Dist: numba~=0.61.2
Requires-Dist: pyyaml~=6.0.2
Requires-Dist: click~=8.1
Requires-Dist: typer~=0.15.2
Requires-Dist: streamlit~=1.45.1
Requires-Dist: matplotlib~=3.10.1
Requires-Dist: plotly~=6.1.2
Requires-Dist: yfinance~=0.2.63
Requires-Dist: tabulate~=0.9.0
Provides-Extra: dev
Requires-Dist: pytest; extra == "dev"
Requires-Dist: pytest-cov; extra == "dev"
Requires-Dist: ruff==0.11.6; extra == "dev"
Requires-Dist: mkdocs; extra == "dev"
Requires-Dist: mkdocs-material; extra == "dev"
Requires-Dist: mkdocstrings[python]; extra == "dev"
Requires-Dist: mkdocs-section-index; extra == "dev"
Requires-Dist: line_profiler; extra == "dev"
Requires-Dist: pre-commit; extra == "dev"
Requires-Dist: codecov; extra == "dev"
Dynamic: license-file
